strava_mcp_server/__init__.py
strava_mcp_server/py.typed
strava_mcp_server/server.py
mseep_strava_mcp_server-0.1.5.dist-info/METADATA
mseep_strava_mcp_server-0.1.5.dist-info/WHEEL
mseep_strava_mcp_server-0.1.5.dist-info/entry_points.txt
mseep_strava_mcp_server-0.1.5.dist-info/licenses/LICENSE
mseep_strava_mcp_server-0.1.5.dist-info/RECORD
