Metadata-Version: 2.4
Name: mseep-strava-mcp-server
Version: 0.1.5
Summary: MCP server for Strava API integration
Author-email: mseep <support@skydeck.ai>
Maintainer-email: mseep <support@skydeck.ai>
License-File: LICENSE
Classifier: Development Status :: 4 - Beta
Classifier: Intended Audience :: Developers
Classifier: License :: OSI Approved :: MIT License
Classifier: Programming Language :: Python :: 3
Classifier: Programming Language :: Python :: 3.12
Classifier: Topic :: Software Development :: Libraries :: Python Modules
Requires-Python: >=3.12
Requires-Dist: fastmcp>=0.1.0
Requires-Dist: httpx>=0.24.0
Requires-Dist: python-dotenv>=1.0.0
Requires-Dist: rich>=13.0.0
Provides-Extra: dev
Requires-Dist: mypy>=1.0.0; extra == 'dev'
Requires-Dist: ruff>=0.1.0; extra == 'dev'
